emod_generic/Eradication.zip
emod_generic/__init__.py
emod_generic/bootstrap.py
emod_generic/schema.zip
emod_generic-2.22.9.dist-info/METADATA
emod_generic-2.22.9.dist-info/WHEEL
emod_generic-2.22.9.dist-info/top_level.txt
emod_generic-2.22.9.dist-info/RECORD
