Metadata-Version: 2.4
Name: emod-generic
Version: 2.22.9
Summary: PyPI distribution of EMOD-Generic files.
Author-email: Kurt Frey <kurt.frey@gatesfoundation.org>
License-Expression: MIT
Project-URL: Homepage, https://www.idmod.org/tool/emod-generic/
Project-URL: Documentation, https://docs.idmod.org/projects/emod-generic/en/latest/
Project-URL: Repository, https://github.com/EMOD-Hub/EMOD-Generic
Project-URL: Issues, https://github.com/EMOD-Hub/EMOD-Generic/issues
Classifier: Operating System :: POSIX :: Linux
Classifier: Programming Language :: C++
Classifier: Topic :: Scientific/Engineering :: Bio-Informatics
Requires-Python: >=3.9
Provides-Extra: docs
Provides-Extra: tests
